Workbook

Sheet Executive Dashboard
A1: سیستم یکپارچه مدیریت کسب‌وکار HMexcelpro
A3: نمای مدیریتی یکپارچه فروش، مالی، موجودی و منابع انسانی
A5: درآمد کل | B5: =SUM(Sales!$H$4:$H$43) -> 214236.81 | D5: سود ناخالص | E5: =SUM(Sales!$J$4:$J$43) -> 137695.81 | G5: هزینه‌های عملیاتی | H5: =SUMIF(Finance!$C$4:$C$39,"Expense",Finance!$F$4:$F$39) -> 50707.2 | J5: سود خالص | K5: =E5-H5 -> 86988.61
A8: ارزش موجودی | B8: =SUM(Inventory!$H$4:$H$11) -> 233809 | D8: اقلام کم‌موجودی | E8: =COUNTIF(Inventory!$F$4:$F$11,"<500") -> 1 | G8: کارکنان فعال | H8: =COUNTIF(HR!$H$4:$H$11,"Active") -> 8 | J8: میانگین عملکرد | K8: =AVERAGE(HR!$G$4:$G$11) -> 89
A11: حاشیه سود | B11: =IF(B5=0,0,K5/B5) -> 0.40603951 | D11: میانگین حضور | E11: =AVERAGE(HR!$F$4:$F$11) -> 0.945 | G11: تعداد فروش | H11: =SUM(Sales!$F$4:$F$43) -> 1789 | J11: موجودی در معرض ریسک | K11: =SUMIF(Inventory!$F$4:$F$11,"<500",Inventory!$H$4:$H$11) -> 33820
A14: ماه | B14: درآمد | C14: سود ناخالص | D14: هزینه‌ها | E14: سهم خالص | G14: محصول | H14: تعداد فروش | I14: درآمد | J14: موجودی فعلی
A15: ژانویه | B15: =SUMIFS(Sales!$H$4:$H$43,Sales!$B$4:$B$43,">="&DATE(2026,1,1),Sales!$B$4:$B$43,"<"&DATE(2026,2,1)) -> 22722.84 | C15: =SUMIFS(Sales!$J$4:$J$43,Sales!$B$4:$B$43,">="&DATE(2026,1,1),Sales!$B$4:$B$43,"<"&DATE(2026,2,1)) -> 14936.84 | D15: =SUMIFS(Finance!$F$4:$F$39,Finance!$C$4:$C$39,"Expense",Finance!$B$4:$B$39,">="&DATE(2026,1,1),Finance!$B$4:$B$39,"<"&DATE(2026,2,1)) -> 28804 | E15: =C15-D15 -> -13867.16 | G15: =Inventory!B4 -> Laptop Stand | H15: =Inventory!E4 -> 244 | I15: =SUMIF(Sales!$D$4:$D$43,G15,Sales!$H$4:$H$43) -> 11583.45 | J15: =Inventory!F4 -> 1256
A16: فوریه | B16: =SUMIFS(Sales!$H$4:$H$43,Sales!$B$4:$B$43,">="&DATE(2026,2,1),Sales!$B$4:$B$43,"<"&DATE(2026,3,1)) -> 18313.95 | C16: =SUMIFS(Sales!$J$4:$J$43,Sales!$B$4:$B$43,">="&DATE(2026,2,1),Sales!$B$4:$B$43,"<"&DATE(2026,3,1)) -> 11405.95 | D16: =SUMIFS(Finance!$F$4:$F$39,Finance!$C$4:$C$39,"Expense",Finance!$B$4:$B$39,">="&DATE(2026,2,1),Finance!$B$4:$B$39,"<"&DATE(2026,3,1)) -> 1746.3 | E16: =C16-D16 -> 9659.65 | G16: =Inventory!B5 -> Wireless Mouse | H16: =Inventory!E5 -> 253 | I16: =SUMIF(Sales!$D$4:$D$43,G16,Sales!$H$4:$H$43) -> 10346.66 | J16: =Inventory!F5 -> 1547
A17: مارس | B17: =SUMIFS(Sales!$H$4:$H$43,Sales!$B$4:$B$43,">="&DATE(2026,3,1),Sales!$B$4:$B$43,"<"&DATE(2026,4,1)) -> 33325.69 | C17: =SUMIFS(Sales!$J$4:$J$43,Sales!$B$4:$B$43,">="&DATE(2026,3,1),Sales!$B$4:$B$43,"<"&DATE(2026,4,1)) -> 21284.69 | D17: =SUMIFS(Finance!$F$4:$F$39,Finance!$C$4:$C$39,"Expense",Finance!$B$4:$B$39,">="&DATE(2026,3,1),Finance!$B$4:$B$39,"<"&DATE(2026,4,1)) -> 4543 | E17: =C17-D17 -> 16741.69 | G17: =Inventory!B6 -> Mechanical Keyboard | H17: =Inventory!E6 -> 199 | I17: =SUMIF(Sales!$D$4:$D$43,G17,Sales!$H$4:$H$43) -> 18438.53 | J17: =Inventory!F6 -> 1001
A18: آوریل | B18: =SUMIFS(Sales!$H$4:$H$43,Sales!$B$4:$B$43,">="&DATE(2026,4,1),Sales!$B$4:$B$43,"<"&DATE(2026,5,1)) -> 16347.61 | C18: =SUMIFS(Sales!$J$4:$J$43,Sales!$B$4:$B$43,">="&DATE(2026,4,1),Sales!$B$4:$B$43,"<"&DATE(2026,5,1)) -> 10327.61 | D18: =SUMIFS(Finance!$F$4:$F$39,Finance!$C$4:$C$39,"Expense",Finance!$B$4:$B$39,">="&DATE(2026,4,1),Finance!$B$4:$B$39,"<"&DATE(2026,5,1)) -> 1746.3 | E18: =C18-D18 -> 8581.31 | G18: =Inventory!B7 -> USB-C Hub | H18: =Inventory!E7 -> 232 | I18: =SUMIF(Sales!$D$4:$D$43,G18,Sales!$H$4:$H$43) -> 13620.42 | J18: =Inventory!F7 -> 1168
A19: مه | B19: =SUMIFS(Sales!$H$4:$H$43,Sales!$B$4:$B$43,">="&DATE(2026,5,1),Sales!$B$4:$B$43,"<"&DATE(2026,6,1)) -> 44879.82 | C19: =SUMIFS(Sales!$J$4:$J$43,Sales!$B$4:$B$43,">="&DATE(2026,5,1),Sales!$B$4:$B$43,"<"&DATE(2026,6,1)) -> 29530.82 | D19: =SUMIFS(Finance!$F$4:$F$39,Finance!$C$4:$C$39,"Expense",Finance!$B$4:$B$39,">="&DATE(2026,5,1),Finance!$B$4:$B$39,"<"&DATE(2026,6,1)) -> 4743 | E19: =C19-D19 -> 24787.82 | G19: =Inventory!B8 -> Office Chair | H19: =Inventory!E8 -> 244 | I19: =SUMIF(Sales!$D$4:$D$43,G19,Sales!$H$4:$H$43) -> 65284.61 | J19: =Inventory!F8 -> 356
A20: ژوئن | B20: =SUMIFS(Sales!$H$4:$H$43,Sales!$B$4:$B$43,">="&DATE(2026,6,1),Sales!$B$4:$B$43,"<"&DATE(2026,7,1)) -> 23723.64 | C20: =SUMIFS(Sales!$J$4:$J$43,Sales!$B$4:$B$43,">="&DATE(2026,6,1),Sales!$B$4:$B$43,"<"&DATE(2026,7,1)) -> 15113.64 | D20: =SUMIFS(Finance!$F$4:$F$39,Finance!$C$4:$C$39,"Expense",Finance!$B$4:$B$39,">="&DATE(2026,6,1),Finance!$B$4:$B$39,"<"&DATE(2026,7,1)) -> 1746.3 | E20: =C20-D20 -> 13367.34 | G20: =Inventory!B9 -> Desk Lamp | H20: =Inventory!E9 -> 195 | I20: =SUMIF(Sales!$D$4:$D$43,G20,Sales!$H$4:$H$43) -> 15256.25 | J20: =Inventory!F9 -> 705
A21: ژوئیه | B21: =SUMIFS(Sales!$H$4:$H$43,Sales!$B$4:$B$43,">="&DATE(2026,7,1),Sales!$B$4:$B$43,"<"&DATE(2026,8,1)) -> 25613.18 | C21: =SUMIFS(Sales!$J$4:$J$43,Sales!$B$4:$B$43,">="&DATE(2026,7,1),Sales!$B$4:$B$43,"<"&DATE(2026,8,1)) -> 16346.18 | D21: =SUMIFS(Finance!$F$4:$F$39,Finance!$C$4:$C$39,"Expense",Finance!$B$4:$B$39,">="&DATE(2026,7,1),Finance!$B$4:$B$39,"<"&DATE(2026,8,1)) -> 4943 | E21: =C21-D21 -> 11403.18 | G21: =Inventory!B10 -> Monitor 24in | H21: =Inventory!E10 -> 183 | I21: =SUMIF(Sales!$D$4:$D$43,G21,Sales!$H$4:$H$43) -> 56519.85 | J21: =Inventory!F10 -> 517
A22: اوت | B22: =SUMIFS(Sales!$H$4:$H$43,Sales!$B$4:$B$43,">="&DATE(2026,8,1),Sales!$B$4:$B$43,"<"&DATE(2026,9,1)) -> 29310.08 | C22: =SUMIFS(Sales!$J$4:$J$43,Sales!$B$4:$B$43,">="&DATE(2026,8,1),Sales!$B$4:$B$43,"<"&DATE(2026,9,1)) -> 18750.08 | D22: =SUMIFS(Finance!$F$4:$F$39,Finance!$C$4:$C$39,"Expense",Finance!$B$4:$B$39,">="&DATE(2026,8,1),Finance!$B$4:$B$39,"<"&DATE(2026,9,1)) -> 1746.3 | E22: =C22-D22 -> 17003.78 | G22: =Inventory!B11 -> Webcam HD | H22: =Inventory!E11 -> 239 | I22: =SUMIF(Sales!$D$4:$D$43,G22,Sales!$H$4:$H$43) -> 23187.04 | J22: =Inventory!F11 -> 611
A23: سپتامبر | B23: =SUMIFS(Sales!$H$4:$H$43,Sales!$B$4:$B$43,">="&DATE(2026,9,1),Sales!$B$4:$B$43,"<"&DATE(2026,10,1)) -> 0 | C23: =SUMIFS(Sales!$J$4:$J$43,Sales!$B$4:$B$43,">="&DATE(2026,9,1),Sales!$B$4:$B$43,"<"&DATE(2026,10,1)) -> 0 | D23: =SUMIFS(Finance!$F$4:$F$39,Finance!$C$4:$C$39,"Expense",Finance!$B$4:$B$39,">="&DATE(2026,9,1),Finance!$B$4:$B$39,"<"&DATE(2026,10,1)) -> 689 | E23: =C23-D23 -> -689
A24: اکتبر | B24: =SUMIFS(Sales!$H$4:$H$43,Sales!$B$4:$B$43,">="&DATE(2026,10,1),Sales!$B$4:$B$43,"<"&DATE(2026,11,1)) -> 0 | C24: =SUMIFS(Sales!$J$4:$J$43,Sales!$B$4:$B$43,">="&DATE(2026,10,1),Sales!$B$4:$B$43,"<"&DATE(2026,11,1)) -> 0 | D24: =SUMIFS(Finance!$F$4:$F$39,Finance!$C$4:$C$39,"Expense",Finance!$B$4:$B$39,">="&DATE(2026,10,1),Finance!$B$4:$B$39,"<"&DATE(2026,11,1)) -> 0 | E24: =C24-D24 -> 0
A25: نوامبر | B25: =SUMIFS(Sales!$H$4:$H$43,Sales!$B$4:$B$43,">="&DATE(2026,11,1),Sales!$B$4:$B$43,"<"&DATE(2026,12,1)) -> 0 | C25: =SUMIFS(Sales!$J$4:$J$43,Sales!$B$4:$B$43,">="&DATE(2026,11,1),Sales!$B$4:$B$43,"<"&DATE(2026,12,1)) -> 0 | D25: =SUMIFS(Finance!$F$4:$F$39,Finance!$C$4:$C$39,"Expense",Finance!$B$4:$B$39,">="&DATE(2026,11,1),Finance!$B$4:$B$39,"<"&DATE(2026,12,1)) -> 0 | E25: =C25-D25 -> 0
A26: دسامبر | B26: =SUMIFS(Sales!$H$4:$H$43,Sales!$B$4:$B$43,">="&DATE(2026,12,1),Sales!$B$4:$B$43,"<"&DATE(2027,1,1)) -> 0 | C26: =SUMIFS(Sales!$J$4:$J$43,Sales!$B$4:$B$43,">="&DATE(2026,12,1),Sales!$B$4:$B$43,"<"&DATE(2027,1,1)) -> 0 | D26: =SUMIFS(Finance!$F$4:$F$39,Finance!$C$4:$C$39,"Expense",Finance!$B$4:$B$39,">="&DATE(2026,12,1),Finance!$B$4:$B$39,"<"&DATE(2027,1,1)) -> 0 | E26: =C26-D26 -> 0

Sheet Sales
A1: فروش و عملکرد کسب‌وکار
A3: شناسه سفارش | B3: تاریخ | C3: شناسه محصول | D3: محصول | E3: فروشنده | F3: تعداد | G3: قیمت واحد | H3: درآمد | I3: بهای تمام‌شده | J3: سود ناخالص
A4: SO-1001 | B4: 46027 | C4: P001 | D4: Laptop Stand | E4: Ava | F4: 28 | G4: 46.26 | H4: =F4*G4 -> 1295.28 | I4: =F4*VLOOKUP(C4,Inventory!$A$4:$G$11,7,FALSE) -> 504 | J4: =H4-I4 -> 791.28
A5: SO-1002 | B5: 46033 | C5: P002 | D5: Wireless Mouse | E5: Liam | F5: 59 | G5: 43.39 | H5: =F5*G5 -> 2560.01 | I5: =F5*VLOOKUP(C5,Inventory!$A$4:$G$11,7,FALSE) -> 826 | J5: =H5-I5 -> 1734.01
A6: SO-1003 | B6: 46039 | C6: P003 | D6: Mechanical Keyboard | E6: Noah | F6: 31 | G6: 92.52 | H6: =F6*G6 -> 2868.12 | I6: =F6*VLOOKUP(C6,Inventory!$A$4:$G$11,7,FALSE) -> 992 | J6: =H6-I6 -> 1876.12
A7: SO-1004 | B7: 46045 | C7: P004 | D7: USB-C Hub | E7: Mia | F7: 67 | G7: 62.83 | H7: =F7*G7 -> 4209.61 | I7: =F7*VLOOKUP(C7,Inventory!$A$4:$G$11,7,FALSE) -> 1474 | J7: =H7-I7 -> 2735.61
A8: SO-1005 | B8: 46051 | C8: P005 | D8: Office Chair | E8: Ava | F8: 42 | G8: 280.71 | H8: =F8*G8 -> 11789.82 | I8: =F8*VLOOKUP(C8,Inventory!$A$4:$G$11,7,FALSE) -> 3990 | J8: =H8-I8 -> 7799.82
A9: SO-1006 | B9: 46057 | C9: P006 | D9: Desk Lamp | E9: Liam | F9: 25 | G9: 71.74 | H9: =F9*G9 -> 1793.5 | I9: =F9*VLOOKUP(C9,Inventory!$A$4:$G$11,7,FALSE) -> 700 | J9: =H9-I9 -> 1093.5
A10: SO-1007 | B10: 46063 | C10: P007 | D10: Monitor 24in | E10: Noah | F10: 23 | G10: 288.6 | H10: =F10*G10 -> 6637.8 | I10: =F10*VLOOKUP(C10,Inventory!$A$4:$G$11,7,FALSE) -> 2530 | J10: =H10-I10 -> 4107.8
A11: SO-1008 | B11: 46069 | C11: P008 | D11: Webcam HD | E11: Mia | F11: 58 | G11: 88.39 | H11: =F11*G11 -> 5126.62 | I11: =F11*VLOOKUP(C11,Inventory!$A$4:$G$11,7,FALSE) -> 2030 | J11: =H11-I11 -> 3096.62
A12: SO-1009 | B12: 46075 | C12: P001 | D12: Laptop Stand | E12: Ava | F12: 55 | G12: 51.83 | H12: =F12*G12 -> 2850.65 | I12: =F12*VLOOKUP(C12,Inventory!$A$4:$G$11,7,FALSE) -> 990 | J12: =H12-I12 -> 1860.65
A13: SO-1010 | B13: 46081 | C13: P002 | D13: Wireless Mouse | E13: Liam | F13: 47 | G13: 40.54 | H13: =F13*G13 -> 1905.38 | I13: =F13*VLOOKUP(C13,Inventory!$A$4:$G$11,7,FALSE) -> 658 | J13: =H13-I13 -> 1247.38
A14: SO-1011 | B14: 46087 | C14: P003 | D14: Mechanical Keyboard | E14: Noah | F14: 23 | G14: 89.73 | H14: =F14*G14 -> 2063.79 | I14: =F14*VLOOKUP(C14,Inventory!$A$4:$G$11,7,FALSE) -> 736 | J14: =H14-I14 -> 1327.79
A15: SO-1012 | B15: 46093 | C15: P004 | D15: USB-C Hub | E15: Mia | F15: 21 | G15: 61.88 | H15: =F15*G15 -> 1299.48 | I15: =F15*VLOOKUP(C15,Inventory!$A$4:$G$11,7,FALSE) -> 462 | J15: =H15-I15 -> 837.48
... A43: SO-1040 | B43: 46261 | C43: P008 | D43: Webcam HD | E43: Mia | F43: 32 | G43: 96.54 | H43: =F43*G43 -> 3089.28 | I43: =F43*VLOOKUP(C43,Inventory!$A$4:$G$11,7,FALSE) -> 1120 | J43: =H43-I43 -> 1969.28

Sheet Finance
A1: مدیریت مالی و هزینه‌ها
A3: شناسه ثبت | B3: تاریخ | C3: نوع | D3: دسته‌بندی | E3: شرح | F3: مبلغ | G3: منبع مرتبط
A4: FN-2001 | B4: 46037 | C4: Expense | D4: حقوق و دستمزد | E4: حقوق ماهانه (متصل به منابع انسانی) | F4: =SUM(HR!$E$4:$E$11) -> 26950 | G4: Operating
A5: FN-2002 | B5: 46047 | C5: Expense | D5: اجاره | E5: هزینه اجاره | F5: 1854 | G5: Operating
A6: FN-2003 | B6: 46057 | C6: Expense | D6: بازاریابی | E6: هزینه بازاریابی | F6: 1007 | G6: Operating
A7: FN-2004 | B7: 46067 | C7: Expense | D7: خدمات و قبوض | E7: هزینه خدمات و قبوض | F7: 420 | G7: Operating
A8: FN-2005 | B8: 46077 | C8: Expense | D8: نرم‌افزار | E8: هزینه نرم‌افزار | F8: 319.3 | G8: Operating
A9: FN-2006 | B9: 46087 | C9: Expense | D9: لجستیک | E9: هزینه لجستیک | F9: 689 | G9: Operating
A10: FN-2007 | B10: 46097 | C10: Expense | D10: حقوق و دستمزد | E10: پاداش / مزایای کارکنان | F10: 2000 | G10: Operating
A11: FN-2008 | B11: 46107 | C11: Expense | D11: اجاره | E11: هزینه اجاره | F11: 1854 | G11: Operating
A12: FN-2009 | B12: 46117 | C12: Expense | D12: بازاریابی | E12: هزینه بازاریابی | F12: 1007 | G12: Operating
A13: FN-2010 | B13: 46127 | C13: Expense | D13: خدمات و قبوض | E13: هزینه خدمات و قبوض | F13: 420 | G13: Operating
A14: FN-2011 | B14: 46137 | C14: Expense | D14: نرم‌افزار | E14: هزینه نرم‌افزار | F14: 319.3 | G14: Operating
A15: FN-2012 | B15: 46147 | C15: Expense | D15: لجستیک | E15: هزینه لجستیک | F15: 689 | G15: Operating
A16: FN-2013 | B16: 46157 | C16: Expense | D16: حقوق و دستمزد | E16: پاداش / مزایای کارکنان | F16: 2200 | G16: Operating
... A27: FN-2024 | B27: 46267 | C27: Expense | D27: لجستیک | E27: هزینه لجستیک | F27: 689 | G27: Operating
A28: FN-3001 | B28: 46050 | C28: Income | D28: Sales Revenue | E28: Sales revenue - month 1 | F28: =SUMIFS(Sales!$H$4:$H$43,Sales!$B$4:$B$43,">="&DATE(2026,1,1),Sales!$B$4:$B$43,"<"&DATE(2026,2,1)) -> 22722.84 | G28: Sales
A29: FN-3002 | B29: 46081 | C29: Income | D29: Sales Revenue | E29: Sales revenue - month 2 | F29: =SUMIFS(Sales!$H$4:$H$43,Sales!$B$4:$B$43,">="&DATE(2026,2,1),Sales!$B$4:$B$43,"<"&DATE(2026,3,1)) -> 18313.95 | G29: Sales
A30: FN-3003 | B30: 46109 | C30: Income | D30: Sales Revenue | E30: Sales revenue - month 3 | F30: =SUMIFS(Sales!$H$4:$H$43,Sales!$B$4:$B$43,">="&DATE(2026,3,1),Sales!$B$4:$B$43,"<"&DATE(2026,4,1)) -> 33325.69 | G30: Sales
A31: FN-3004 | B31: 46140 | C31: Income | D31: Sales Revenue | E31: Sales revenue - month 4 | F31: =SUMIFS(Sales!$H$4:$H$43,Sales!$B$4:$B$43,">="&DATE(2026,4,1),Sales!$B$4:$B$43,"<"&DATE(2026,5,1)) -> 16347.61 | G31: Sales
A32: FN-3005 | B32: 46170 | C32: Income | D32: Sales Revenue | E32: Sales revenue - month 5 | F32: =SUMIFS(Sales!$H$4:$H$43,Sales!$B$4:$B$43,">="&DATE(2026,5,1),Sales!$B$4:$B$43,"<"&DATE(2026,6,1)) -> 44879.82 | G32: Sales
A33: FN-3006 | B33: 46201 | C33: Income | D33: Sales Revenue | E33: Sales revenue - month 6 | F33: =SUMIFS(Sales!$H$4:$H$43,Sales!$B$4:$B$43,">="&DATE(2026,6,1),Sales!$B$4:$B$43,"<"&DATE(2026,7,1)) -> 23723.64 | G33: Sales
A34: FN-3007 | B34: 46231 | C34: Income | D34: Sales Revenue | E34: Sales revenue - month 7 | F34: =SUMIFS(Sales!$H$4:$H$43,Sales!$B$4:$B$43,">="&DATE(2026,7,1),Sales!$B$4:$B$43,"<"&DATE(2026,8,1)) -> 25613.18 | G34: Sales
A35: FN-3008 | B35: 46262 | C35: Income | D35: Sales Revenue | E35: Sales revenue - month 8 | F35: =SUMIFS(Sales!$H$4:$H$43,Sales!$B$4:$B$43,">="&DATE(2026,8,1),Sales!$B$4:$B$43,"<"&DATE(2026,9,1)) -> 29310.08 | G35: Sales
A36: FN-3009 | B36: 46293 | C36: Income | D36: Sales Revenue | E36: Sales revenue - month 9 | F36: =SUMIFS(Sales!$H$4:$H$43,Sales!$B$4:$B$43,">="&DATE(2026,9,1),Sales!$B$4:$B$43,"<"&DATE(2026,10,1)) -> 0 | G36: Sales
A37: FN-3010 | B37: 46323 | C37: Income | D37: Sales Revenue | E37: Sales revenue - month 10 | F37: =SUMIFS(Sales!$H$4:$H$43,Sales!$B$4:$B$43,">="&DATE(2026,10,1),Sales!$B$4:$B$43,"<"&DATE(2026,11,1)) -> 0 | G37: Sales
A38: FN-3011 | B38: 46354 | C38: Income | D38: Sales Revenue | E38: Sales revenue - month 11 | F38: =SUMIFS(Sales!$H$4:$H$43,Sales!$B$4:$B$43,">="&DATE(2026,11,1),Sales!$B$4:$B$43,"<"&DATE(2026,12,1)) -> 0 | G38: Sales
A39: FN-3012 | B39: 46384 | C39: Income | D39: Sales Revenue | E39: Sales revenue - month 12 | F39: =SUMIFS(Sales!$H$4:$H$43,Sales!$B$4:$B$43,">="&DATE(2026,12,1),Sales!$B$4:$B$43,"<"&DATE(2027,1,1)) -> 0 | G39: Sales

Sheet Inventory
A1: مدیریت موجودی
A3: شناسه محصول | B3: محصول | C3: دسته‌بندی | D3: موجودی اولیه | E3: تعداد فروش | F3: موجودی فعلی | G3: هزینه واحد | H3: ارزش موجودی
A4: P001 | B4: Laptop Stand | C4: لوازم جانبی | D4: 1500 | E4: =SUMIF(Sales!$C$4:$C$43,A4,Sales!$F$4:$F$43) -> 244 | F4: =D4-E4 -> 1256 | G4: 18 | H4: =F4*G4 -> 22608
A5: P002 | B5: Wireless Mouse | C5: الکترونیک | D5: 1800 | E5: =SUMIF(Sales!$C$4:$C$43,A5,Sales!$F$4:$F$43) -> 253 | F5: =D5-E5 -> 1547 | G5: 14 | H5: =F5*G5 -> 21658
A6: P003 | B6: Mechanical Keyboard | C6: الکترونیک | D6: 1200 | E6: =SUMIF(Sales!$C$4:$C$43,A6,Sales!$F$4:$F$43) -> 199 | F6: =D6-E6 -> 1001 | G6: 32 | H6: =F6*G6 -> 32032
A7: P004 | B7: USB-C Hub | C7: الکترونیک | D7: 1400 | E7: =SUMIF(Sales!$C$4:$C$43,A7,Sales!$F$4:$F$43) -> 232 | F7: =D7-E7 -> 1168 | G7: 22 | H7: =F7*G7 -> 25696
A8: P005 | B8: Office Chair | C8: مبلمان | D8: 600 | E8: =SUMIF(Sales!$C$4:$C$43,A8,Sales!$F$4:$F$43) -> 244 | F8: =D8-E8 -> 356 | G8: 95 | H8: =F8*G8 -> 33820
A9: P006 | B9: Desk Lamp | C9: مبلمان | D9: 900 | E9: =SUMIF(Sales!$C$4:$C$43,A9,Sales!$F$4:$F$43) -> 195 | F9: =D9-E9 -> 705 | G9: 28 | H9: =F9*G9 -> 19740
A10: P007 | B10: Monitor 24in | C10: الکترونیک | D10: 700 | E10: =SUMIF(Sales!$C$4:$C$43,A10,Sales!$F$4:$F$43) -> 183 | F10: =D10-E10 -> 517 | G10: 110 | H10: =F10*G10 -> 56870
A11: P008 | B11: Webcam HD | C11: الکترونیک | D11: 850 | E11: =SUMIF(Sales!$C$4:$C$43,A11,Sales!$F$4:$F$43) -> 239 | F11: =D11-E11 -> 611 | G11: 35 | H11: =F11*G11 -> 21385

Sheet HR
A1: منابع انسانی و عملکرد کارکنان
A3: شناسه کارمند | B3: نام کارمند | C3: واحد | D3: سمت | E3: حقوق ماهانه | F3: درصد حضور | G3: امتیاز عملکرد | H3: وضعیت
A4: E001 | B4: Ava Carter | C4: فروش | D4: مدیر فروش | E4: 4200 | F4: 0.96 | G4: 92 | H4: Active
A5: E002 | B5: Liam Reed | C5: فروش | D5: کارشناس فروش | E5: 3200 | F5: 0.94 | G5: 88 | H5: Active
A6: E003 | B6: Noah King | C6: فروش | D6: کارشناس فروش | E6: 3100 | F6: 0.91 | G6: 84 | H6: Active
A7: E004 | B7: Mia Scott | C7: فروش | D7: کارشناس فروش | E7: 3150 | F7: 0.97 | G7: 94 | H7: Active
A8: E005 | B8: Emma Young | C8: مالی | D8: حسابدار | E8: 3600 | F8: 0.95 | G8: 90 | H8: Active
A9: E006 | B9: Lucas Hall | C9: عملیات | D9: مسئول موجودی | E9: 3000 | F9: 0.93 | G9: 86 | H9: Active
A10: E007 | B10: Sophia Green | C10: منابع انسانی | D10: کارشناس منابع انسانی | E10: 3400 | F10: 0.98 | G10: 93 | H10: Active
A11: E008 | B11: Ethan Baker | C11: عملیات | D11: تحلیلگر عملیات | E11: 3300 | F11: 0.92 | G11: 85 | H11: Active

Sheet Instructions
A1: راهنمای کاربر — سیستم یکپارچه مدیریت کسب‌وکار HMexcelpro
A4: بخش | B4: هدف | C4: نحوه ارتباط
A5: داشبورد مدیریتی | B5: نمای مرکزی مدیریت برای درآمد، سود، هزینه‌ها، موجودی و شاخص‌های منابع انسانی. | C5: اطلاعات را با فرمول‌های زنده از چهار ماژول عملیاتی دریافت می‌کند.
A6: فروش | B6: داده‌های سفارش با درآمد، بهای تمام‌شده و سود ناخالص. | C6: هزینه محصول از موجودی می‌آید؛ درآمد به مالی و داشبورد منتقل می‌شود.
A7: مالی | B7: هزینه‌های عملیاتی به‌همراه درآمد فروش. | C7: ردیف حقوق به داده‌های منابع انسانی و درآمد فروش به ماژول فروش متصل است.
A8: موجودی | B8: موجودی اولیه، تعداد فروش، موجودی فعلی و ارزش موجودی. | C8: تعداد فروش از تراکنش‌های ماژول فروش محاسبه می‌شود.
A9: منابع انسانی | B9: اطلاعات کارکنان، حقوق، حضور و عملکرد. | C9: هزینه حقوق در ماژول مالی از مجموع حقوق منابع انسانی استفاده می‌کند.
A10: ورود داده | B10: داده‌های نمونه را با دقت جایگزین کنید و فرمول‌های ستون‌های محاسباتی را حفظ کنید. | C10: داده‌های نمونه برای نمایش ارتباط کامل ماژول‌ها در نمونه‌کار قرار داده شده‌اند.
A11: سازگاری | B11: فایل استاندارد .xlsx و بدون ماکرو طراحی شده است. | C11: در Excel دسکتاپ یا موبایل باز کنید؛ نمودارها در داشبورد مدیریتی متمرکز هستند.
